<metadata xml:lang="zh"><Esri><CreaDate>20181128</CreaDate><CreaTime>09122000</CreaTime><ArcGISFormat>1.0</ArcGISFormat><SyncOnce>FALSE</SyncOnce><DataProperties><itemProps><itemName Sync="TRUE">研究影像WGS.tif</itemName><imsContentType Sync="TRUE">002</imsContentType><nativeExtBox><westBL Sync="TRUE">115.441173</westBL><eastBL Sync="TRUE">115.456248</eastBL><southBL Sync="TRUE">-0.151146</southBL><northBL Sync="TRUE">-0.134691</northBL><exTypeCode Sync="TRUE">1</exTypeCode></nativeExtBox><itemLocation><linkage Sync="TRUE">file://D:\DATA\上午C\研究影像WGS.tif</linkage><protocol Sync="TRUE">Local Area Network</protocol></itemLocation></itemProps><coordRef><type Sync="TRUE">Geographic</type><geogcsn Sync="TRUE">GCS_WGS_1984</geogcsn><csUnits Sync="TRUE">Angular Unit: Degree (0.017453)</csUnits><peXml Sync="TRUE">&lt;GeographicCoordinateSystem xsi:type='typens:GeographicCoordinateSystem' xmlns:xsi='http://www.w3.org/2001/XMLSchema-instance' xmlns:xs='http://www.w3.org/2001/XMLSchema' xmlns:typens='http://www.esri.com/schemas/ArcGIS/10.6'&gt;&lt;WKT&gt;GEOGCS[&amp;quot;GCS_WGS_1984&amp;quot;,DATUM[&amp;quot;D_WGS_1984&amp;quot;,SPHEROID[&amp;quot;WGS_1984&amp;quot;,6378137.0,298.257223563]],PRIMEM[&amp;quot;Greenwich&amp;quot;,0.0],UNIT[&amp;quot;Degree&amp;quot;,0.0174532925199433],AUTHORITY[&amp;quot;EPSG&amp;quot;,4326]]&lt;/WKT&gt;&lt;XOrigin&gt;-400&lt;/XOrigin&gt;&lt;YOrigin&gt;-400&lt;/YOrigin&gt;&lt;XYScale&gt;11258999068426.238&lt;/XYScale&gt;&lt;ZOrigin&gt;-100000&lt;/ZOrigin&gt;&lt;ZScale&gt;10000&lt;/ZScale&gt;&lt;MOrigin&gt;-100000&lt;/MOrigin&gt;&lt;MScale&gt;10000&lt;/MScale&gt;&lt;XYTolerance&gt;8.983152841195215e-09&lt;/XYTolerance&gt;&lt;ZTolerance&gt;0.001&lt;/ZTolerance&gt;&lt;MTolerance&gt;0.001&lt;/MTolerance&gt;&lt;HighPrecision&gt;true&lt;/HighPrecision&gt;&lt;LeftLongitude&gt;-180&lt;/LeftLongitude&gt;&lt;WKID&gt;4326&lt;/WKID&gt;&lt;LatestWKID&gt;4326&lt;/LatestWKID&gt;&lt;/GeographicCoordinateSystem&gt;</peXml></coordRef><lineage><Process ToolSource="c:\program files (x86)\arcgis\desktop10.6\ArcToolbox\Toolboxes\Data Management Tools.tbx\ProjectRaster" Date="20181128" Time="091220">ProjectRaster 带校准 D:\DATA\上午C\编辑3D.gdb\投影待校准 GEOGCS['GCS_WGS_1984',DATUM['D_WGS_1984',SPHEROID['WGS_1984',6378137.0,298.257223563]],PRIMEM['Greenwich',0.0],UNIT['Degree',0.0174532925199433]] NEAREST "4.49328136294744E-06 4.49328136294744E-06" # # PROJCS['Shanghai',GEOGCS['GCS_WGS_1984',DATUM['D_WGS_1984',SPHEROID['WGS_1984',6378137.0,298.257223563]],PRIMEM['Greenwich',0.0],UNIT['Degree',0.0174532925199433]],PROJECTION['Transverse_Mercator'],PARAMETER['false_easting',500000.0],PARAMETER['false_northing',0.0],PARAMETER['central_meridian',120.0],PARAMETER['scale_factor',1.0],PARAMETER['latitude_of_origin',0.0],UNIT['Meter',1.0]]</Process><Process ToolSource="c:\program files (x86)\arcgis\desktop10.6\ArcToolbox\Toolboxes\Data Management Tools.tbx\CopyRaster" Date="20181128" Time="093622">CopyRaster D:\DATA\上午C\编辑3D.gdb\投影待校准 D:\DATA\上午C\研究影像WGS.tif # # 256 NONE NONE # NONE NONE TIFF NONE</Process></lineage><RasterProperties><General><PixelDepth Sync="TRUE">8</PixelDepth><HasColormap Sync="TRUE">FALSE</HasColormap><CompressionType Sync="TRUE">LZW</CompressionType><NumBands Sync="TRUE">3</NumBands><Format Sync="TRUE">TIFF</Format><HasPyramids Sync="TRUE">TRUE</HasPyramids><SourceType Sync="TRUE">continuous</SourceType><PixelType Sync="TRUE">unsigned integer</PixelType><NoDataValue Sync="TRUE">256</NoDataValue></General></RasterProperties></DataProperties><SyncDate>20181128</SyncDate><SyncTime>09362200</SyncTime><ModDate>20181128</ModDate><ModTime>09362200</ModTime></Esri><dataIdInfo><envirDesc Sync="TRUE"> Version 6.2 (Build 9200) ; Esri ArcGIS 10.6.0.8321</envirDesc><dataLang><languageCode value="zho" Sync="TRUE"></languageCode><countryCode value="CHN" Sync="TRUE"></countryCode></dataLang><idCitation><resTitle Sync="TRUE">研究影像WGS.tif</resTitle><presForm><PresFormCd value="005" Sync="TRUE"></PresFormCd></presForm></idCitation><spatRpType><SpatRepTypCd value="002" Sync="TRUE"></SpatRepTypCd></spatRpType><dataExt><geoEle><GeoBndBox esriExtentType="search"><exTypeCode Sync="TRUE">1</exTypeCode><westBL Sync="TRUE">115.441173</westBL><eastBL Sync="TRUE">115.456248</eastBL><northBL Sync="TRUE">-0.134691</northBL><southBL Sync="TRUE">-0.151146</southBL></GeoBndBox></geoEle></dataExt></dataIdInfo><mdLang><languageCode value="zho" Sync="TRUE"></languageCode><countryCode value="CHN" Sync="TRUE"></countryCode></mdLang><distInfo><distFormat><formatName Sync="TRUE">栅格数据集</formatName></distFormat></distInfo><mdHrLv><ScopeCd value="005" Sync="TRUE"></ScopeCd></mdHrLv><mdHrLvName Sync="TRUE">dataset</mdHrLvName><refSysInfo><RefSystem><refSysID><identCode code="4326" Sync="TRUE"></identCode><idCodeSpace Sync="TRUE">EPSG</idCodeSpace><idVersion Sync="TRUE">6.14(3.0.1)</idVersion></refSysID></RefSystem></refSysInfo><spdoinfo><rastinfo><rasttype Sync="TRUE">Pixel</rasttype><rowcount Sync="TRUE">3662</rowcount><colcount Sync="TRUE">3355</colcount><rastxsz Sync="TRUE">0.000004</rastxsz><rastysz Sync="TRUE">0.000004</rastysz><rastbpp Sync="TRUE">8</rastbpp><vrtcount Sync="TRUE">1</vrtcount><rastorig Sync="TRUE">Upper Left</rastorig><rastcmap Sync="TRUE">FALSE</rastcmap><rastcomp Sync="TRUE">LZ77</rastcomp><rastband Sync="TRUE">3</rastband><rastdtyp Sync="TRUE">pixel codes</rastdtyp><rastifor Sync="TRUE">FGDBR</rastifor><rastplyr Sync="TRUE">TRUE</rastplyr></rastinfo></spdoinfo><spref><horizsys><planar><planci><plance Sync="TRUE">row and column</plance><coordrep><absres Sync="TRUE">0.000004</absres><ordres Sync="TRUE">0.000004</ordres></coordrep></planci></planar></horizsys></spref><mdDateSt Sync="TRUE">20181128</mdDateSt><spatRepInfo><Georect><cellGeo><CellGeoCd Sync="TRUE" value="002"></CellGeoCd></cellGeo><numDims Sync="TRUE">2</numDims><tranParaAv Sync="TRUE">1</tranParaAv><chkPtAv Sync="TRUE">0</chkPtAv><cornerPts><pos Sync="TRUE">115.441173 -0.151146</pos></cornerPts><cornerPts><pos Sync="TRUE">115.441173 -0.134691</pos></cornerPts><cornerPts><pos Sync="TRUE">115.456248 -0.134691</pos></cornerPts><cornerPts><pos Sync="TRUE">115.456248 -0.151146</pos></cornerPts><centerPt><pos Sync="TRUE">115.448710 -0.142919</pos></centerPt><axisDimension type="002"><dimSize Sync="TRUE">3355</dimSize><dimResol><value Sync="TRUE">0.000004</value></dimResol></axisDimension><axisDimension type="001"><dimSize Sync="TRUE">3662</dimSize><dimResol><value Sync="TRUE">0.000004</value></dimResol></axisDimension><ptInPixel><PixOrientCd Sync="TRUE" value="001"></PixOrientCd></ptInPixel></Georect></spatRepInfo><contInfo><ImgDesc><contentTyp><ContentTypCd Sync="TRUE" value="001"></ContentTypCd></contentTyp><covDim><Band><dimDescrp Sync="TRUE">Band_1</dimDescrp><maxVal Sync="TRUE">255.000000</maxVal><minVal Sync="TRUE">0.000000</minVal><bitsPerVal Sync="TRUE">8</bitsPerVal></Band><Band><dimDescrp Sync="TRUE">Band_2</dimDescrp><maxVal Sync="TRUE">255.000000</maxVal><minVal Sync="TRUE">0.000000</minVal><bitsPerVal Sync="TRUE">8</bitsPerVal></Band><Band><dimDescrp Sync="TRUE">Band_3</dimDescrp><maxVal Sync="TRUE">255.000000</maxVal><minVal Sync="TRUE">0.000000</minVal><bitsPerVal Sync="TRUE">8</bitsPerVal></Band></covDim></ImgDesc></contInfo></metadata>
